LICENSE
README.md
VERSION
requirements.txt
setup.py
texta_bert_tagger/attributions.py
texta_bert_tagger/config.py
texta_bert_tagger/exceptions.py
texta_bert_tagger/tagger.py
texta_bert_tagger/tagging_report.py
texta_bert_tagger/validators.py
texta_bert_tagger.egg-info/PKG-INFO
texta_bert_tagger.egg-info/SOURCES.txt
texta_bert_tagger.egg-info/dependency_links.txt
texta_bert_tagger.egg-info/requires.txt
texta_bert_tagger.egg-info/top_level.txt