Metadata-Version: 2.1
Name: texta-bert-tagger
Version: 3.0.1
Summary: texta-bert-tagger
Home-page: https://git.texta.ee/texta/texta-bert-tagger-python
Author: TEXTA
Author-email: info@texta.ee
License: GPLv3
License-File: LICENSE
